{"name":"build-javascript","namedChunkGroups":{"polyfill":{"name":"polyfill","assets":[{"name":"webpack-runtime-3dccd722e1677ca48233.js","size":5735},{"name":"polyfill-3f2c32fc75f950a6a70e.js","size":85042}],"filteredAssets":0,"assetsSize":90777,"filteredAuxiliaryAssets":2,"auxiliaryAssetsSize":232477},"app":{"name":"app","assets":[{"name":"webpack-runtime-3dccd722e1677ca48233.js","size":5735},{"name":"framework-d97d9f6873b979a42797.js","size":150186},{"name":"app-251c36e5578287a135d6.js","size":301189}],"filteredAssets":0,"assetsSize":457110,"filteredAuxiliaryAssets":24,"auxiliaryAssetsSize":4876729},"component---src-components-page-templates-blog-page-tsx":{"name":"component---src-components-page-templates-blog-page-tsx","assets":[{"name":"styles.a4a99d64ff31b0ebbe9d.css","size":225122},{"name":"framework-d97d9f6873b979a42797.js","size":150186},{"name":"c4ec0132-a1c027616e1a7e5e4899.js","size":464147},{"name":"132ee8da-b878493970126f1816db.js","size":354661},{"name":"7e91b273-b885e7f74c5ba61d5179.js","size":163973},{"name":"commons-a3fcf52bc17691bc5b8d.js","size":135193},{"name":"5362dffe27923e249f40e4ba698d14ab4771a0f9-37df661748d34bcfb404.js","size":239635},{"name":"99f28a3450395f2941534da4854146b600be20a6-60fef565b56f8a753320.js","size":23302},{"name":"component---src-components-page-templates-blog-page-tsx-0f64b33b4df2d61751c2.js","size":3128}],"filteredAssets":0,"assetsSize":1759347,"filteredAuxiliaryAssets":20,"auxiliaryAssetsSize":4577503},"component---src-components-page-templates-info-page-tsx":{"name":"component---src-components-page-templates-info-page-tsx","assets":[{"name":"styles.a4a99d64ff31b0ebbe9d.css","size":225122},{"name":"framework-d97d9f6873b979a42797.js","size":150186},{"name":"c4ec0132-a1c027616e1a7e5e4899.js","size":464147},{"name":"132ee8da-b878493970126f1816db.js","size":354661},{"name":"7e91b273-b885e7f74c5ba61d5179.js","size":163973},{"name":"commons-a3fcf52bc17691bc5b8d.js","size":135193},{"name":"5362dffe27923e249f40e4ba698d14ab4771a0f9-37df661748d34bcfb404.js","size":239635},{"name":"component---src-components-page-templates-info-page-tsx-7b670089e3bbefe7932c.js","size":772}],"filteredAssets":0,"assetsSize":1733689,"filteredAuxiliaryAssets":19,"auxiliaryAssetsSize":4444786},"component---src-pages-404-tsx":{"name":"component---src-pages-404-tsx","assets":[{"name":"styles.a4a99d64ff31b0ebbe9d.css","size":225122},{"name":"framework-d97d9f6873b979a42797.js","size":150186},{"name":"c4ec0132-a1c027616e1a7e5e4899.js","size":464147},{"name":"132ee8da-b878493970126f1816db.js","size":354661},{"name":"7e91b273-b885e7f74c5ba61d5179.js","size":163973},{"name":"commons-a3fcf52bc17691bc5b8d.js","size":135193},{"name":"5362dffe27923e249f40e4ba698d14ab4771a0f9-37df661748d34bcfb404.js","size":239635},{"name":"component---src-pages-404-tsx-80742085dbeffddd208b.js","size":466}],"filteredAssets":0,"assetsSize":1733383,"filteredAuxiliaryAssets":19,"auxiliaryAssetsSize":4442715},"component---src-pages-blog-tsx":{"name":"component---src-pages-blog-tsx","assets":[{"name":"styles.a4a99d64ff31b0ebbe9d.css","size":225122},{"name":"commons-a3fcf52bc17691bc5b8d.js","size":135193},{"name":"99f28a3450395f2941534da4854146b600be20a6-60fef565b56f8a753320.js","size":23302},{"name":"component---src-pages-blog-tsx-c25b4303c7a52ff68e44.js","size":1047}],"filteredAssets":0,"assetsSize":384664,"filteredAuxiliaryAssets":15,"auxiliaryAssetsSize":826453},"component---src-pages-contact-tsx":{"name":"component---src-pages-contact-tsx","assets":[{"name":"styles.a4a99d64ff31b0ebbe9d.css","size":225122},{"name":"framework-d97d9f6873b979a42797.js","size":150186},{"name":"c4ec0132-a1c027616e1a7e5e4899.js","size":464147},{"name":"132ee8da-b878493970126f1816db.js","size":354661},{"name":"7e91b273-b885e7f74c5ba61d5179.js","size":163973},{"name":"commons-a3fcf52bc17691bc5b8d.js","size":135193},{"name":"5362dffe27923e249f40e4ba698d14ab4771a0f9-37df661748d34bcfb404.js","size":239635},{"name":"component---src-pages-contact-tsx-cc867f4aa014e2623ecb.js","size":572}],"filteredAssets":0,"assetsSize":1733489,"filteredAuxiliaryAssets":19,"auxiliaryAssetsSize":4443106},"component---src-pages-index-tsx":{"name":"component---src-pages-index-tsx","assets":[{"name":"styles.a4a99d64ff31b0ebbe9d.css","size":225122},{"name":"framework-d97d9f6873b979a42797.js","size":150186},{"name":"c4ec0132-a1c027616e1a7e5e4899.js","size":464147},{"name":"132ee8da-b878493970126f1816db.js","size":354661},{"name":"7e91b273-b885e7f74c5ba61d5179.js","size":163973},{"name":"commons-a3fcf52bc17691bc5b8d.js","size":135193},{"name":"5362dffe27923e249f40e4ba698d14ab4771a0f9-37df661748d34bcfb404.js","size":239635},{"name":"component---src-pages-index-tsx-73a0472fb92de8fa1ecd.js","size":569}],"filteredAssets":0,"assetsSize":1733486,"filteredAuxiliaryAssets":19,"auxiliaryAssetsSize":4443117}},"assetsByChunkName":{"polyfill":["webpack-runtime-3dccd722e1677ca48233.js","polyfill-3f2c32fc75f950a6a70e.js"],"app":["webpack-runtime-3dccd722e1677ca48233.js","framework-d97d9f6873b979a42797.js","app-251c36e5578287a135d6.js"],"component---src-components-page-templates-blog-page-tsx":["styles.a4a99d64ff31b0ebbe9d.css","framework-d97d9f6873b979a42797.js","c4ec0132-a1c027616e1a7e5e4899.js","132ee8da-b878493970126f1816db.js","7e91b273-b885e7f74c5ba61d5179.js","commons-a3fcf52bc17691bc5b8d.js","5362dffe27923e249f40e4ba698d14ab4771a0f9-37df661748d34bcfb404.js","99f28a3450395f2941534da4854146b600be20a6-60fef565b56f8a753320.js","component---src-components-page-templates-blog-page-tsx-0f64b33b4df2d61751c2.js"],"component---src-components-page-templates-info-page-tsx":["styles.a4a99d64ff31b0ebbe9d.css","framework-d97d9f6873b979a42797.js","c4ec0132-a1c027616e1a7e5e4899.js","132ee8da-b878493970126f1816db.js","7e91b273-b885e7f74c5ba61d5179.js","commons-a3fcf52bc17691bc5b8d.js","5362dffe27923e249f40e4ba698d14ab4771a0f9-37df661748d34bcfb404.js","component---src-components-page-templates-info-page-tsx-7b670089e3bbefe7932c.js"],"component---src-pages-404-tsx":["styles.a4a99d64ff31b0ebbe9d.css","framework-d97d9f6873b979a42797.js","c4ec0132-a1c027616e1a7e5e4899.js","132ee8da-b878493970126f1816db.js","7e91b273-b885e7f74c5ba61d5179.js","commons-a3fcf52bc17691bc5b8d.js","5362dffe27923e249f40e4ba698d14ab4771a0f9-37df661748d34bcfb404.js","component---src-pages-404-tsx-80742085dbeffddd208b.js"],"component---src-pages-blog-tsx":["styles.a4a99d64ff31b0ebbe9d.css","commons-a3fcf52bc17691bc5b8d.js","99f28a3450395f2941534da4854146b600be20a6-60fef565b56f8a753320.js","component---src-pages-blog-tsx-c25b4303c7a52ff68e44.js"],"component---src-pages-contact-tsx":["styles.a4a99d64ff31b0ebbe9d.css","framework-d97d9f6873b979a42797.js","c4ec0132-a1c027616e1a7e5e4899.js","132ee8da-b878493970126f1816db.js","7e91b273-b885e7f74c5ba61d5179.js","commons-a3fcf52bc17691bc5b8d.js","5362dffe27923e249f40e4ba698d14ab4771a0f9-37df661748d34bcfb404.js","component---src-pages-contact-tsx-cc867f4aa014e2623ecb.js"],"component---src-pages-index-tsx":["styles.a4a99d64ff31b0ebbe9d.css","framework-d97d9f6873b979a42797.js","c4ec0132-a1c027616e1a7e5e4899.js","132ee8da-b878493970126f1816db.js","7e91b273-b885e7f74c5ba61d5179.js","commons-a3fcf52bc17691bc5b8d.js","5362dffe27923e249f40e4ba698d14ab4771a0f9-37df661748d34bcfb404.js","component---src-pages-index-tsx-73a0472fb92de8fa1ecd.js"]},"childAssetsByChunkName":{}}